misanthropic/__init__.py
misanthropic-1.0.dist-info/METADATA
misanthropic-1.0.dist-info/WHEEL
misanthropic-1.0.dist-info/RECORD
