Metadata-Version: 2.4
Name: misanthropic
Version: 1.0
Summary: Write your own code
Requires-Python: >=3.13
